mkdocs_flux/__init__.py
mkdocs_flux/base.html
mkdocs_flux/main.html
mkdocs_flux/mkdocs_theme.yml
mkdocs_flux/nav.html
mkdocs_flux/tab.html
mkdocs_flux/toc.html
mkdocs_flux/css/notebook.css
mkdocs_flux/css/pygments.css
mkdocs_flux/css/theme.css
mkdocs_flux/js/mike.js
mkdocs_flux/svg/sprite.svg
mkdocs_flux-0.0.6.dist-info/METADATA
mkdocs_flux-0.0.6.dist-info/WHEEL
mkdocs_flux-0.0.6.dist-info/entry_points.txt
mkdocs_flux-0.0.6.dist-info/licenses/LICENSE.txt
mkdocs_flux-0.0.6.dist-info/RECORD
